px4stack/__init__.py
px4stack/config.py
px4stack/context.py
px4stack/py.typed
px4stack/stack.py
px4stack-1.0.0a5.dist-info/WHEEL
px4stack-1.0.0a5.dist-info/METADATA
px4stack-1.0.0a5.dist-info/RECORD
