Metadata-Version: 2.1
Name: px4stack
Version: 1.0.0a5
Summary: 
Author: Quinn Thibeault
Author-email: quinn.thibeault96@gmail.com
Requires-Python: >=3.6,<3.10
Classifier: Programming Language :: Python :: 3
Classifier: Programming Language :: Python :: 3.6
Classifier: Programming Language :: Python :: 3.7
Classifier: Programming Language :: Python :: 3.8
Classifier: Programming Language :: Python :: 3.9
Requires-Dist: attrs (>=21.0.0,<22.0.0)
Requires-Dist: docker (>=5.0.0,<6.0.0)
